{
	"format_version": "1.8.0",
	"animations": {
		"idle": {
			"loop": true,
			"animation_length": 2,
			"bones": {
				"arms": {
					"rotation": {
						"0.0": {
							"vector": [0, 0, 0]
						},
						"0.9583": {
							"vector": [5, 0, 0]
						},
						"2.0": {
							"vector": [0, 0, 0]
						}
					}
				},
				"right_arm": {
					"rotation": {
						"0.0": {
							"vector": [0, 0, 0]
						},
						"0.9583": {
							"vector": [-1.5, 0, -2.5]
						},
						"2.0": {
							"vector": [0, 0, 0]
						}
					}
				},
				"left_arm": {
					"rotation": {
						"0.0": {
							"vector": [0, 0, 0]
						},
						"0.9583": {
							"vector": [-1.5, 0, 2.5]
						},
						"2.0": {
							"vector": [0, 0, 0]
						}
					}
				},
				"b_main": {
					"rotation": {
						"0.0": {
							"vector": [0, 0, 0]
						},
						"0.9583": {
							"vector": [-4, 0, 0]
						},
						"2.0": {
							"vector": [0, 0, 0]
						}
					}
				},
				"h_head": {
					"rotation": {
						"0.0": {
							"vector": [0, 0, 0]
						},
						"0.9583": {
							"vector": [6, 0, 0]
						},
						"2.0": {
							"vector": [0, 0, 0]
						}
					}
				},
				"mouth": {
					"rotation": {
						"0.0": {
							"vector": [0, 0, 0]
						},
						"1.0": {
							"vector": [-5, 0, 0]
						},
						"2.0": {
							"vector": [0, 0, 0]
						}
					}
				}
			}
		},
		"walk": {
			"loop": true,
			"animation_length": 1.5,
			"bones": {
				"model": {
					"rotation": {
						"0.0": {
							"vector": [0, 0, 0]
						},
						"1.5": {
							"vector": [0, 0, 0]
						}
					},
					"position": {
						"0.0": {
							"vector": [0, 0, 0]
						},
						"0.75": {
							"vector": [0, -0.5, 0]
						},
						"1.5": {
							"vector": [0, 0, 0]
						}
					}
				},
				"right_arm": {
					"rotation": {
						"0.0": {
							"vector": [-7.49294, 0.32621, 2.47864]
						},
						"0.7917": {
							"vector": [7.5, 0, 0]
						},
						"1.5": {
							"vector": [-7.49294, 0.32621, 2.47864]
						}
					}
				},
				"left_arm": {
					"rotation": {
						"0.0": {
							"vector": [7.49294, 0.32621, -2.47864]
						},
						"0.7917": {
							"vector": [-7.5, 0, 0]
						},
						"1.5": {
							"vector": [7.49294, 0.32621, -2.47864]
						}
					}
				},
				"left_leg": {
					"rotation": {
						"0.0": {
							"vector": [-15, 0, 0]
						},
						"0.75": {
							"vector": [15, 0, 0]
						},
						"1.5": {
							"vector": [-15, 0, 0]
						}
					},
					"position": {
						"0.0": {
							"vector": [0, 0, 0]
						},
						"0.75": {
							"vector": [0, 0, 0]
						},
						"1.125": {
							"vector": [0, 2.5, -0.3]
						},
						"1.5": {
							"vector": [0, 0, 0]
						}
					}
				},
				"right_leg": {
					"rotation": {
						"0.0": {
							"vector": [15, 0, 0]
						},
						"0.75": {
							"vector": [-15, 0, 0]
						},
						"1.5": {
							"vector": [15, 0, 0]
						}
					},
					"position": {
						"0.0": {
							"vector": [0, 0, 0]
						},
						"0.375": {
							"vector": [0, 2.5, -0.3]
						},
						"0.75": {
							"vector": [0, 0, 0]
						},
						"1.5": {
							"vector": [0, 0, 0]
						}
					}
				},
				"b_main": {
					"rotation": {
						"0.0": {
							"vector": [0, 0, 0]
						},
						"1.5": {
							"vector": [0, 0, 0]
						}
					},
					"position": {
						"0.0": {
							"vector": [0, 0, 0]
						},
						"1.5": {
							"vector": [0, 0, 0]
						}
					}
				},
				"h_head": {
					"rotation": {
						"0.0": {
							"vector": [0, 0, 0]
						},
						"0.75": {
							"vector": [10, 0, 0]
						},
						"1.5": {
							"vector": [0, 0, 0]
						}
					}
				},
				"mouth": {
					"rotation": {
						"0.0": {
							"vector": [0, 0, 0]
						},
						"0.75": {
							"vector": [-8, 0, 0]
						},
						"1.5": {
							"vector": [0, 0, 0]
						}
					}
				}
			}
		}
	},
	"geckolib_format_version": 2
}